escapyst/__init__.py
escapyst/c.py
escapyst/printf.py
escapyst-0.0.2.dist-info/METADATA
escapyst-0.0.2.dist-info/WHEEL
escapyst-0.0.2.dist-info/top_level.txt
escapyst-0.0.2.dist-info/RECORD
