Metadata-Version: 2.4
Name: escapyst
Version: 0.0.2
Summary: Package implementing Binary<->String codecs based on escape sequences
Author: Jérôme Carretero
License: MIT License
Project-URL: Homepage, https://gitlab.com/exmakhina/escapyst
Project-URL: Download, https://pypi.python.org/pypi/escapyst
Keywords: persistent
Classifier: License :: OSI Approved :: MIT License
Classifier: Programming Language :: Python :: 3
Classifier: Intended Audience :: Developers
Dynamic: summary
